[
 {
  "doctype": "Number Card",
  "name": "Available Units",
  "label": "Available Units",
  "document_type": "Item",
  "function": "Count",
  "filters_json": "[[\"Item\",\"unit_status\",\"=\",\"Available\"]]",
  "color": "#4CAF50",
  "is_public": 1,
  "module": "Real Estate"
 },
 {
  "doctype": "Number Card",
  "name": "Active Bookings",
  "label": "Active Bookings",
  "document_type": "Property Booking",
  "function": "Count",
  "filters_json": "[[\"Property Booking\",\"docstatus\",\"=\",1],[\"Property Booking\",\"status\",\"!=\",\"Cancelled\"]]",
  "color": "#2196F3",
  "is_public": 1,
  "module": "Real Estate"
 },
 {
  "doctype": "Number Card",
  "name": "Pending PDCs",
  "label": "Pending PDCs",
  "document_type": "PDC Entry",
  "function": "Count",
  "filters_json": "[[\"PDC Entry\",\"status\",\"=\",\"Pending\"]]",
  "color": "#FF9800",
  "is_public": 1,
  "module": "Real Estate"
 },
 {
  "doctype": "Number Card",
  "name": "Bounced PDCs",
  "label": "Bounced PDCs",
  "document_type": "PDC Entry",
  "function": "Count",
  "filters_json": "[[\"PDC Entry\",\"status\",\"=\",\"Bounced\"]]",
  "color": "#F44336",
  "is_public": 1,
  "module": "Real Estate"
 }
]
